daggerml/__about__.py
daggerml/__init__.py
daggerml/core.py
daggerml/util.py
daggerml-0.0.38.post3.dist-info/METADATA
daggerml-0.0.38.post3.dist-info/WHEEL
daggerml-0.0.38.post3.dist-info/licenses/LICENSE
daggerml-0.0.38.post3.dist-info/RECORD
