Metadata-Version: 2.4
Name: daggerml
Version: 0.0.38.post3
Summary: DaggerML
Project-URL: Homepage, https://daggerml.com
Project-URL: Documentation, https://daggerml.com
Project-URL: Issues, https://github.com/daggerml/python-lib/issues
Project-URL: Source, https://github.com/daggerml/python-lib
Project-URL: License, https://github.com/daggerml/python-lib/blob/master/LICENSE
Author-email: DaggerML <engineering@daggerml.com>
License-Expression: MIT
License-File: LICENSE
Classifier: Development Status :: 4 - Beta
Classifier: License :: OSI Approved :: MIT License
Classifier: Operating System :: OS Independent
Classifier: Programming Language :: Python
Classifier: Programming Language :: Python :: 3
Classifier: Programming Language :: Python :: 3.9
Classifier: Programming Language :: Python :: 3.10
Classifier: Programming Language :: Python :: 3.11
Classifier: Programming Language :: Python :: 3.12
Classifier: Programming Language :: Python :: 3.13
Classifier: Programming Language :: Python :: Implementation :: PyPy
Requires-Python: >=3.9
Provides-Extra: cli
Requires-Dist: daggerml-cli>=0.0.38; extra == 'cli'
Provides-Extra: dev
Requires-Dist: moto[all,server]; extra == 'dev'
Requires-Dist: pytest; extra == 'dev'
Requires-Dist: pytest-cov; extra == 'dev'
